pyln/spec/bolt4/__init__.py
pyln/spec/bolt4/bolt.py
pyln/spec/bolt4/csv.py
pyln/spec/bolt4/gen_csv_version.py
pyln/spec/bolt4/gen_version.py
pyln/spec/bolt4/text.py
pyln_bolt4-1.0.222.dist-info/WHEEL
pyln_bolt4-1.0.222.dist-info/METADATA
pyln_bolt4-1.0.222.dist-info/RECORD
