Metadata-Version: 2.1
Name: pyln-bolt4
Version: 1.0.222
Summary: A pure python implementation of BOLT4
License: MIT
Author: Rusty Russell
Author-email: rusty@blockstream.com
Requires-Python: >=3.7,<4.0
Classifier: License :: OSI Approved :: MIT License
Classifier: Programming Language :: Python :: 3
Classifier: Programming Language :: Python :: 3.10
Classifier: Programming Language :: Python :: 3.7
Classifier: Programming Language :: Python :: 3.8
Classifier: Programming Language :: Python :: 3.9
